Metadata-Version: 2.1
Name: tfrelease
Version: 0.1.0
Summary: 'Fetches metadata from Terraform releases'
Home-page: https://github.com/hansohn/tfrelease
Author: Ryan Hansohn
Author-email: info@imnorobot.com
License: Apache License 2.0
Project-URL: Bug Tracker, https://github.com/hansohn/tfrelease/issues
Project-URL: Source Code, https://github.com/hansohn/tfrelease
Keywords: terraform,release
Platform: UNKNOWN
Classifier: Intended Audience :: Developers
Classifier: Intended Audience :: System Administrators
Classifier: License :: OSI Approved :: Apache Software License
Classifier: Programming Language :: Python :: 3.9
Requires-Python: ~=3.9
License-File: LICENSE
